LICENSE.txt
MANIFEST.in
README.rst
setup.cfg
setup.py
brutus/__init__.py
brutus.egg-info/PKG-INFO
brutus.egg-info/SOURCES.txt
brutus.egg-info/dependency_links.txt
brutus.egg-info/entry_points.txt
brutus.egg-info/top_level.txt