Metadata-Version: 1.1
Name: brutus
Version: 0.0.1
Summary: Brute force your software into working order
Home-page: https://github.com/akoumjian/brutus
Author: Alec Koumjian
Author-email: akoumjian@gmail.com
License: MIT
Keywords: automation configuration
Platform: UNKNOWN
Classifier: Development Status :: 3 - Alpha
Classifier: Intended Audience :: Developers
Classifier: Topic :: Software Development :: Build Tools
Classifier: License :: OSI Approved :: MIT License
Classifier: Programming Language :: Python :: 2
Classifier: Programming Language :: Python :: 2.6
Classifier: Programming Language :: Python :: 2.7
Classifier: Programming Language :: Python :: 3
Classifier: Programming Language :: Python :: 3.3
Classifier: Programming Language :: Python :: 3.4
Classifier: Programming Language :: Python :: 3.5
